[
  {
    "id": "064f6a2f-5b5b-4bc6-807d-8c88889214bf",
    "user_id": "78b840d1-bc69-4b68-b41f-61c682335dd2",
    "user_email": "leducbec@gmail.com",
    "action": "CREATE_PROJECT",
    "detail": "Tạo dự án: ABC",
    "created_at": "2026-04-11T15:35:22.425996+00:00"
  },
  {
    "id": "c29e2ac7-d310-4cd7-b89b-7cd881e7d10b",
    "user_id": "b60416d2-388a-4d37-9008-fd77bb42be25",
    "user_email": "ducle@greenviet.net",
    "action": "UPDATE_STATUS",
    "detail": "Task: Storage and Collection of Recyclables → in-progress",
    "created_at": "2026-04-13T01:24:07.795146+00:00"
  },
  {
    "id": "6b2f0a80-32ec-4938-80a5-296c90ff697c",
    "user_id": "b60416d2-388a-4d37-9008-fd77bb42be25",
    "user_email": "ducle@greenviet.net",
    "action": "UPDATE_STATUS",
    "detail": "Task: Storage and Collection of Recyclables → not-started",
    "created_at": "2026-04-13T01:24:08.685018+00:00"
  },
  {
    "id": "e16c7ed3-aeb4-40d5-8dcb-7dddc47244eb",
    "user_id": "b60416d2-388a-4d37-9008-fd77bb42be25",
    "user_email": "ducle@greenviet.net",
    "action": "CREATE_PROJECT",
    "detail": "Tạo dự án: XYZ",
    "created_at": "2026-04-14T06:09:45.333767+00:00"
  },
  {
    "id": "5b9cfa20-2d23-4476-83cb-7fa6c9b77819",
    "user_id": "b60416d2-388a-4d37-9008-fd77bb42be25",
    "user_email": "ducle@greenviet.net",
    "action": "CREATE_USER",
    "detail": "Tạo user: minhducle33@gmail.com (Beta - member)",
    "created_at": "2026-04-14T07:29:53.085945+00:00"
  },
  {
    "id": "29b864c2-828a-4cda-9f2e-19e24a920de4",
    "user_id": "ba080462-2b3f-40a5-b321-5a8b872d1d59",
    "user_email": "minhducle33@gmail.com",
    "action": "UPDATE_USER",
    "detail": "Cập nhật Admin GreenViet: Beta/admin",
    "created_at": "2026-04-14T07:33:33.261806+00:00"
  },
  {
    "id": "b986a4de-b055-4ea8-abb7-6c94493cec4c",
    "user_id": "ba080462-2b3f-40a5-b321-5a8b872d1d59",
    "user_email": "minhducle33@gmail.com",
    "action": "UPDATE_USER",
    "detail": "Cập nhật Admin GreenViet: Beta/admin",
    "created_at": "2026-04-14T07:33:45.186346+00:00"
  },
  {
    "id": "7fb9fd5e-13ff-4c9f-893f-e43878f9282a",
    "user_id": "ba080462-2b3f-40a5-b321-5a8b872d1d59",
    "user_email": "minhducle33@gmail.com",
    "action": "UPDATE_USER",
    "detail": "Cập nhật Tran Vn: Beta/admin",
    "created_at": "2026-04-14T07:34:17.747737+00:00"
  },
  {
    "id": "fcb046e2-a3ac-421b-8027-7219608921f8",
    "user_id": "ba080462-2b3f-40a5-b321-5a8b872d1d59",
    "user_email": "minhducle33@gmail.com",
    "action": "UPDATE_USER",
    "detail": "Cập nhật Tran Vn: Beta/member",
    "created_at": "2026-04-14T07:35:02.269558+00:00"
  },
  {
    "id": "35407f87-801f-4a3b-9dc0-e62acf3a354a",
    "user_id": "ba080462-2b3f-40a5-b321-5a8b872d1d59",
    "user_email": "minhducle33@gmail.com",
    "action": "UPDATE_USER",
    "detail": "Cập nhật Admin GreenViet: team=Beta, role=admin",
    "created_at": "2026-04-14T07:59:58.216463+00:00"
  },
  {
    "id": "75f8e02d-4b6b-4f50-83f7-72d14096cb92",
    "user_id": "ba080462-2b3f-40a5-b321-5a8b872d1d59",
    "user_email": "minhducle33@gmail.com",
    "action": "UPDATE_USER",
    "detail": "Cập nhật Admin GreenViet: team=Alpha, role=member",
    "created_at": "2026-04-14T08:00:28.299549+00:00"
  },
  {
    "id": "0c4cb3db-318b-441c-8dac-f2185bdee7c6",
    "user_id": "ba080462-2b3f-40a5-b321-5a8b872d1d59",
    "user_email": "minhducle33@gmail.com",
    "action": "UPDATE_USER",
    "detail": "Cập nhật Admin GreenViet: team=Alpha, role=member",
    "created_at": "2026-04-14T08:01:05.761258+00:00"
  },
  {
    "id": "4e4810ec-175b-449b-a298-775684ea422d",
    "user_id": "ba080462-2b3f-40a5-b321-5a8b872d1d59",
    "user_email": "minhducle33@gmail.com",
    "action": "UPDATE_STATUS",
    "detail": "ssfsfs → na",
    "created_at": "2026-04-14T08:08:01.745387+00:00"
  },
  {
    "id": "f5e95011-8de5-4f6f-8376-a205b8e03c57",
    "user_id": "ba080462-2b3f-40a5-b321-5a8b872d1d59",
    "user_email": "minhducle33@gmail.com",
    "action": "UPDATE_STATUS",
    "detail": "ssfsfs → na",
    "created_at": "2026-04-14T08:08:03.421346+00:00"
  },
  {
    "id": "a43651f6-f25f-47df-a69a-c035f5dfad07",
    "user_id": "ba080462-2b3f-40a5-b321-5a8b872d1d59",
    "user_email": "minhducle33@gmail.com",
    "action": "UPDATE_STATUS",
    "detail": "ssfsfs → na",
    "created_at": "2026-04-14T08:08:07.892119+00:00"
  },
  {
    "id": "f9d83286-c2f0-4b97-a2f1-28f7dcf72a9f",
    "user_id": "ba080462-2b3f-40a5-b321-5a8b872d1d59",
    "user_email": "minhducle33@gmail.com",
    "action": "UPDATE_STATUS",
    "detail": "ssfsfs → na",
    "created_at": "2026-04-14T08:08:14.607499+00:00"
  },
  {
    "id": "a0df081b-7c45-4c74-bba5-e3894efc41fe",
    "user_id": "b60416d2-388a-4d37-9008-fd77bb42be25",
    "user_email": "ducle@greenviet.net",
    "action": "UPDATE_USER",
    "detail": "Cập nhật Tran Vn: team=Gamma, role=member",
    "created_at": "2026-04-14T08:13:12.010212+00:00"
  },
  {
    "id": "d0c4dea3-7b2c-49d9-a129-bf345ad0f995",
    "user_id": "b60416d2-388a-4d37-9008-fd77bb42be25",
    "user_email": "ducle@greenviet.net",
    "action": "UPDATE_USER",
    "detail": "Cập nhật Tran Vn: team=Gamma, role=member",
    "created_at": "2026-04-14T08:14:05.839618+00:00"
  },
  {
    "id": "7a5d4e1f-c8ae-4f4b-9829-a90f05435389",
    "user_id": "78b840d1-bc69-4b68-b41f-61c682335dd2",
    "user_email": "leducbec@gmail.com",
    "action": "CREATE_PROJECT",
    "detail": "Tạo dự án: JHVV",
    "created_at": "2026-04-14T08:17:53.038506+00:00"
  },
  {
    "id": "0af6e2f7-eaa5-48e3-9cc2-e86a81d6ab62",
    "user_id": "b60416d2-388a-4d37-9008-fd77bb42be25",
    "user_email": "ducle@greenviet.net",
    "action": "UPDATE_USER",
    "detail": "Cập nhật Tran Vn: team=Gamma, role=member",
    "created_at": "2026-04-14T08:33:37.393818+00:00"
  },
  {
    "id": "50d814f9-bcf9-4f71-9be0-492397c183e4",
    "user_id": "b60416d2-388a-4d37-9008-fd77bb42be25",
    "user_email": "ducle@greenviet.net",
    "action": "UPDATE_USER",
    "detail": "Cập nhật Tran Vn: team=Delta, role=member",
    "created_at": "2026-04-14T08:34:15.577608+00:00"
  },
  {
    "id": "b295d490-921d-4474-a527-8b9d3bf72cd1",
    "user_id": "b60416d2-388a-4d37-9008-fd77bb42be25",
    "user_email": "ducle@greenviet.net",
    "action": "UPDATE_USER",
    "detail": "Cập nhật Tran Vn: team=Delta, role=member",
    "created_at": "2026-04-14T08:37:37.435309+00:00"
  },
  {
    "id": "fac725e6-3810-445a-bc56-071c118fea1a",
    "user_id": "b60416d2-388a-4d37-9008-fd77bb42be25",
    "user_email": "ducle@greenviet.net",
    "action": "DELETE_USER",
    "detail": "Xóa user: ba080462-2b3f-40a5-b321-5a8b872d1d59",
    "created_at": "2026-04-14T08:38:54.802625+00:00"
  },
  {
    "id": "86fe3448-3689-49f1-96ca-e0df02e71f3b",
    "user_id": "b60416d2-388a-4d37-9008-fd77bb42be25",
    "user_email": "ducle@greenviet.net",
    "action": "DELETE_USER",
    "detail": "Xóa user: ba080462-2b3f-40a5-b321-5a8b872d1d59",
    "created_at": "2026-04-14T08:58:03.147238+00:00"
  },
  {
    "id": "4cf5e1ee-425d-4163-b9f7-2a2d73622f36",
    "user_id": "b60416d2-388a-4d37-9008-fd77bb42be25",
    "user_email": "ducle@greenviet.net",
    "action": "UPDATE_USER",
    "detail": "Cập nhật Tran Vn: team=Gamma, role=member",
    "created_at": "2026-04-15T02:02:05.720109+00:00"
  },
  {
    "id": "3d690a28-c69a-4911-8200-9d82a2db2248",
    "user_id": "b60416d2-388a-4d37-9008-fd77bb42be25",
    "user_email": "ducle@greenviet.net",
    "action": "UPDATE_USER",
    "detail": "Cập nhật Tran Vn: team=Delta, role=member",
    "created_at": "2026-04-15T02:03:05.805332+00:00"
  },
  {
    "id": "17356836-a9ec-438d-95c1-f32a7b90310a",
    "user_id": "b60416d2-388a-4d37-9008-fd77bb42be25",
    "user_email": "ducle@greenviet.net",
    "action": "UPDATE_USER",
    "detail": "Cập nhật Tran Vn: team=Gamma, role=member",
    "created_at": "2026-04-15T02:08:24.638881+00:00"
  },
  {
    "id": "7e359156-abbe-4377-89b5-7a332e2ebb30",
    "user_id": "b60416d2-388a-4d37-9008-fd77bb42be25",
    "user_email": "ducle@greenviet.net",
    "action": "UPDATE_USER",
    "detail": "Cập nhật Tran Vn: team=Delta, role=member",
    "created_at": "2026-04-15T03:40:34.412523+00:00"
  },
  {
    "id": "d4d950da-737f-45e9-b9ea-43b9d4795ea3",
    "user_id": "b60416d2-388a-4d37-9008-fd77bb42be25",
    "user_email": "ducle@greenviet.net",
    "action": "UPDATE_USER",
    "detail": "Cập nhật Tran Vn: team=Beta, role=member",
    "created_at": "2026-04-17T09:06:11.53761+00:00"
  },
  {
    "id": "8f49eabd-0602-48b0-910c-a343744e54d4",
    "user_id": "ba080462-2b3f-40a5-b321-5a8b872d1d59",
    "user_email": "minhducle33@gmail.com",
    "action": "UPDATE_STATUS",
    "detail": "LEED for Neighborhood Development Location → completed",
    "created_at": "2026-04-17T09:06:58.014487+00:00"
  },
  {
    "id": "1ee941d9-7f84-4ab4-a5b7-3384c2cf873e",
    "user_id": "ba080462-2b3f-40a5-b321-5a8b872d1d59",
    "user_email": "minhducle33@gmail.com",
    "action": "UPDATE_STATUS",
    "detail": "LEED for Neighborhood Development Location → in-progress",
    "created_at": "2026-04-17T09:07:35.510278+00:00"
  },
  {
    "id": "42b054bd-2473-4e37-b504-c712e0597cee",
    "user_id": "b60416d2-388a-4d37-9008-fd77bb42be25",
    "user_email": "ducle@greenviet.net",
    "action": "CREATE_PROJECT",
    "detail": "Tạo dự án: gvdjgvjkgvj",
    "created_at": "2026-04-17T09:11:23.831434+00:00"
  },
  {
    "id": "28169db7-1487-414b-a995-3396aaf582c0",
    "user_id": "b60416d2-388a-4d37-9008-fd77bb42be25",
    "user_email": "ducle@greenviet.net",
    "action": "UPDATE_STATUS",
    "detail": "Sensitive Land Protection → completed",
    "created_at": "2026-04-17T13:54:26.739752+00:00"
  },
  {
    "id": "176d8975-871a-455c-ba3a-54fa62fc034d",
    "user_id": "b60416d2-388a-4d37-9008-fd77bb42be25",
    "user_email": "ducle@greenviet.net",
    "action": "DELETE_PROJECT",
    "detail": "Xóa dự án: JHVV",
    "created_at": "2026-04-17T14:43:13.481877+00:00"
  },
  {
    "id": "254d92e6-8c19-4a65-bdc2-1efa4b53cd8d",
    "user_id": "b60416d2-388a-4d37-9008-fd77bb42be25",
    "user_email": "ducle@greenviet.net",
    "action": "UPDATE_USER",
    "detail": "Cập nhật Tran Vn: team=Gamma, role=member",
    "created_at": "2026-04-17T14:45:24.391752+00:00"
  },
  {
    "id": "1bc214a4-45ad-4939-89bc-11a0cc93783b",
    "user_id": "b60416d2-388a-4d37-9008-fd77bb42be25",
    "user_email": "ducle@greenviet.net",
    "action": "UPDATE_USER",
    "detail": "Cập nhật Beta Team Lead: team=Gamma, role=lead",
    "created_at": "2026-04-17T14:45:49.057815+00:00"
  },
  {
    "id": "df72ff93-f630-429b-b832-b1fa22dad6ca",
    "user_id": "ba080462-2b3f-40a5-b321-5a8b872d1d59",
    "user_email": "minhducle33@gmail.com",
    "action": "DELETE_PROJECT",
    "detail": "Xóa dự án: gvdjgvjkgvj",
    "created_at": "2026-04-18T09:32:31.285195+00:00"
  },
  {
    "id": "8b224061-a04b-4b5a-9bc0-d7000d782baa",
    "user_id": "ba080462-2b3f-40a5-b321-5a8b872d1d59",
    "user_email": "minhducle33@gmail.com",
    "action": "SUBMIT_TASK",
    "detail": "Submit: Integrative Process",
    "created_at": "2026-04-18T09:34:04.06097+00:00"
  },
  {
    "id": "31bddbbc-9805-4c24-89ab-d8de1bc27317",
    "user_id": "ba080462-2b3f-40a5-b321-5a8b872d1d59",
    "user_email": "minhducle33@gmail.com",
    "action": "CREATE_PROJECT",
    "detail": "Tạo dự án: jhjhjh",
    "created_at": "2026-04-18T09:34:43.060851+00:00"
  },
  {
    "id": "e51da31f-f2f8-4e21-a50c-f0aa83077ac5",
    "user_id": "ba080462-2b3f-40a5-b321-5a8b872d1d59",
    "user_email": "minhducle33@gmail.com",
    "action": "UPDATE_STATUS",
    "detail": "LEED for Neighborhood Development Location → completed",
    "created_at": "2026-04-18T09:35:31.119041+00:00"
  },
  {
    "id": "5d5a16ed-acf3-4426-84c7-dde996c40f81",
    "user_id": "ba080462-2b3f-40a5-b321-5a8b872d1d59",
    "user_email": "minhducle33@gmail.com",
    "action": "SUBMIT_TASK",
    "detail": "Submit: LEED for Neighborhood Development Location",
    "created_at": "2026-04-18T09:35:33.441459+00:00"
  },
  {
    "id": "4e98aa86-123f-4f8d-b0ef-0f90dd554e6e",
    "user_id": "b60416d2-388a-4d37-9008-fd77bb42be25",
    "user_email": "ducle@greenviet.net",
    "action": "APPROVE_TASK",
    "detail": "Approve: Integrative Process",
    "created_at": "2026-04-18T09:37:11.327699+00:00"
  },
  {
    "id": "833fdcd9-5236-402a-9242-f13bdb6040f4",
    "user_id": "b60416d2-388a-4d37-9008-fd77bb42be25",
    "user_email": "ducle@greenviet.net",
    "action": "APPROVE_TASK",
    "detail": "Approve: LEED for Neighborhood Development Location",
    "created_at": "2026-04-18T09:37:17.244976+00:00"
  },
  {
    "id": "f1fef7ee-8e0f-4cde-9412-d25736f12bd2",
    "user_id": "ba080462-2b3f-40a5-b321-5a8b872d1d59",
    "user_email": "minhducle33@gmail.com",
    "action": "SUBMIT_TASK",
    "detail": "Submit: Sensitive Land Protection",
    "created_at": "2026-04-18T09:42:24.462621+00:00"
  },
  {
    "id": "fc61f593-b2a0-4cda-9c96-44b24a9cc588",
    "user_id": "ba080462-2b3f-40a5-b321-5a8b872d1d59",
    "user_email": "minhducle33@gmail.com",
    "action": "UPDATE_STATUS",
    "detail": "High Priority Site and Equitable Development → completed",
    "created_at": "2026-04-18T09:42:29.569615+00:00"
  },
  {
    "id": "147cdf0f-c120-4527-865f-a1ac43f3a50c",
    "user_id": "ba080462-2b3f-40a5-b321-5a8b872d1d59",
    "user_email": "minhducle33@gmail.com",
    "action": "SUBMIT_TASK",
    "detail": "Submit: High Priority Site and Equitable Development",
    "created_at": "2026-04-18T09:42:32.765781+00:00"
  },
  {
    "id": "c07134d7-62b6-4540-a86e-30dcb55b9ff0",
    "user_id": "ba080462-2b3f-40a5-b321-5a8b872d1d59",
    "user_email": "minhducle33@gmail.com",
    "action": "UPDATE_STATUS",
    "detail": "Surrounding Density and Diverse Uses → in-progress",
    "created_at": "2026-04-18T09:42:37.105755+00:00"
  },
  {
    "id": "db739912-eaaa-471c-b2d0-b780200787b9",
    "user_id": "ba080462-2b3f-40a5-b321-5a8b872d1d59",
    "user_email": "minhducle33@gmail.com",
    "action": "SUBMIT_TASK",
    "detail": "Submit: Surrounding Density and Diverse Uses",
    "created_at": "2026-04-18T09:42:38.896754+00:00"
  },
  {
    "id": "096ad931-d907-470d-8535-108ed2620cd1",
    "user_id": "ba080462-2b3f-40a5-b321-5a8b872d1d59",
    "user_email": "minhducle33@gmail.com",
    "action": "UPDATE_STATUS",
    "detail": "Integrative Process → in-progress",
    "created_at": "2026-04-18T09:43:29.971223+00:00"
  },
  {
    "id": "791ac8cd-9a00-4de5-bf67-fe86a968c5d0",
    "user_id": "78b840d1-bc69-4b68-b41f-61c682335dd2",
    "user_email": "leducbec@gmail.com",
    "action": "REJECT_TASK",
    "detail": "Reject: Sensitive Land Protection — ngoc nghech",
    "created_at": "2026-04-18T09:49:54.217955+00:00"
  },
  {
    "id": "b5ddaada-21fa-4439-a5be-c61ece09a77d",
    "user_id": "78b840d1-bc69-4b68-b41f-61c682335dd2",
    "user_email": "leducbec@gmail.com",
    "action": "APPROVE_TASK",
    "detail": "Approve: High Priority Site and Equitable Development",
    "created_at": "2026-04-18T09:50:01.425119+00:00"
  },
  {
    "id": "62c31c5c-5feb-485c-8ecb-65f6d16ea81a",
    "user_id": "78b840d1-bc69-4b68-b41f-61c682335dd2",
    "user_email": "leducbec@gmail.com",
    "action": "APPROVE_TASK",
    "detail": "Approve: Surrounding Density and Diverse Uses",
    "created_at": "2026-04-18T09:50:03.531325+00:00"
  },
  {
    "id": "34ff3d9d-5d79-4341-be23-02befa6c0c9a",
    "user_id": "78b840d1-bc69-4b68-b41f-61c682335dd2",
    "user_email": "leducbec@gmail.com",
    "action": "UPDATE_STATUS",
    "detail": "Integrative Process → completed",
    "created_at": "2026-04-20T01:46:07.412742+00:00"
  },
  {
    "id": "78ed7ec6-3006-496c-b2fd-560f5ac17b64",
    "user_id": "ba080462-2b3f-40a5-b321-5a8b872d1d59",
    "user_email": "minhducle33@gmail.com",
    "action": "SUBMIT_TASK",
    "detail": "Submit: Access to Quality Transit",
    "created_at": "2026-04-20T07:23:40.347224+00:00"
  },
  {
    "id": "0a6bbc51-2d7a-4550-9257-f8d9caf60a86",
    "user_id": "ba080462-2b3f-40a5-b321-5a8b872d1d59",
    "user_email": "minhducle33@gmail.com",
    "action": "SUBMIT_TASK",
    "detail": "Submit: Bicycle Facilities",
    "created_at": "2026-04-20T07:23:43.372057+00:00"
  },
  {
    "id": "3fcb73b9-57b4-40a7-be41-270010b60502",
    "user_id": "b60416d2-388a-4d37-9008-fd77bb42be25",
    "user_email": "ducle@greenviet.net",
    "action": "APPROVE_TASK",
    "detail": "Approve: Access to Quality Transit",
    "created_at": "2026-04-20T08:20:30.131774+00:00"
  },
  {
    "id": "1de2c86e-f53e-403a-8f5c-a75c3af2f384",
    "user_id": "b60416d2-388a-4d37-9008-fd77bb42be25",
    "user_email": "ducle@greenviet.net",
    "action": "APPROVE_TASK",
    "detail": "Approve: Bicycle Facilities",
    "created_at": "2026-04-20T08:20:31.359882+00:00"
  },
  {
    "id": "8a174dd4-bc84-4fd6-810a-3ee0e4f8e093",
    "user_id": "ba080462-2b3f-40a5-b321-5a8b872d1d59",
    "user_email": "minhducle33@gmail.com",
    "action": "UPDATE_STATUS",
    "detail": "Sensitive Land Protection → completed",
    "created_at": "2026-04-20T08:39:01.003021+00:00"
  },
  {
    "id": "35ff345f-c2b7-4360-bc20-f865da02746e",
    "user_id": "ba080462-2b3f-40a5-b321-5a8b872d1d59",
    "user_email": "minhducle33@gmail.com",
    "action": "SUBMIT_TASK",
    "detail": "Submit: Sensitive Land Protection",
    "created_at": "2026-04-20T08:39:21.189326+00:00"
  },
  {
    "id": "c5bc8447-9390-4dd9-abfc-56cfa02ea3e2",
    "user_id": "b60416d2-388a-4d37-9008-fd77bb42be25",
    "user_email": "ducle@greenviet.net",
    "action": "APPROVE_TASK",
    "detail": "Approve: Sensitive Land Protection",
    "created_at": "2026-04-20T08:40:29.668502+00:00"
  },
  {
    "id": "26ae7925-6b4a-4ba8-a04a-0ec439326e88",
    "user_id": "b60416d2-388a-4d37-9008-fd77bb42be25",
    "user_email": "ducle@greenviet.net",
    "action": "REOPEN_TASK",
    "detail": "Reopen: Integrative Process",
    "created_at": "2026-04-20T08:43:10.16104+00:00"
  },
  {
    "id": "e698a4c3-da28-4ece-9ed9-6ae4f5c27b6c",
    "user_id": "ba080462-2b3f-40a5-b321-5a8b872d1d59",
    "user_email": "minhducle33@gmail.com",
    "action": "REOPEN_TASK",
    "detail": "Reopen: c966e1e1-7079-4547-a84e-1107049c1b70",
    "created_at": "2026-04-20T08:43:36.958029+00:00"
  },
  {
    "id": "1f1dd485-5cee-4295-a8d2-0d2d266b37f3",
    "user_id": "ba080462-2b3f-40a5-b321-5a8b872d1d59",
    "user_email": "minhducle33@gmail.com",
    "action": "SUBMIT_TASK",
    "detail": "Submit: Integrative Process",
    "created_at": "2026-04-20T08:44:26.043523+00:00"
  },
  {
    "id": "f558b718-a3d2-42d2-8a04-0e96df1bb6b5",
    "user_id": "ba080462-2b3f-40a5-b321-5a8b872d1d59",
    "user_email": "minhducle33@gmail.com",
    "action": "UPDATE_STATUS",
    "detail": "Integrative Process → completed",
    "created_at": "2026-04-20T08:44:30.754995+00:00"
  },
  {
    "id": "a558b4e4-7764-4297-976c-eee9439e25a0",
    "user_id": "78b840d1-bc69-4b68-b41f-61c682335dd2",
    "user_email": "leducbec@gmail.com",
    "action": "CREATE_PROJECT",
    "detail": "Tạo dự án: jfjvhjvhmhv",
    "created_at": "2026-04-21T01:56:26.026253+00:00"
  }
]